aionova/__init__.py
aionova/anova.py
aionova/exceptions.py
aionova/legacy.py
aionova-0.0.6.dist-info/LICENSE.txt
aionova-0.0.6.dist-info/METADATA
aionova-0.0.6.dist-info/WHEEL
aionova-0.0.6.dist-info/top_level.txt
aionova-0.0.6.dist-info/RECORD
