Metadata-Version: 2.1
Name: aionova
Version: 0.0.6
Summary: A simple asyncio based library for communicating with Anova Precision Cookers
Home-page: https://github.com/kmdm/aionova
Author: Kenny Millington
Author-email: kenny@kennynet.co.uk
License: UNKNOWN
Platform: UNKNOWN
Classifier: Programming Language :: Python :: 3
Classifier: License :: OSI Approved :: MIT License
Classifier: Operating System :: OS Independent
Requires-Python: >=3.6
License-File: LICENSE.txt
Requires-Dist: aiohttp
